passkit/init.py
passkit/ct/__init__.py
passkit/ct/scheduler/__init__.py
passkit/ct/scheduler/scheduler_pb2.py
passkit/ct/scheduler/scheduler_pb2_grpc.py
passkit/io/__init__.py
passkit/io/analytics/__init__.py
passkit/io/analytics/a_rpc_pb2.py
passkit/io/analytics/a_rpc_pb2_grpc.py
passkit/io/certificate/__init__.py
passkit/io/certificate/certificate_pb2.py
passkit/io/certificate/certificate_pb2_grpc.py
passkit/io/common/__init__.py
passkit/io/common/attributes_pb2.py
passkit/io/common/attributes_pb2_grpc.py
passkit/io/common/billing_pb2.py
passkit/io/common/billing_pb2_grpc.py
passkit/io/common/common_objects_pb2.py
passkit/io/common/common_objects_pb2_grpc.py
passkit/io/common/distribution_pb2.py
passkit/io/common/distribution_pb2_grpc.py
passkit/io/common/expiry_pb2.py
passkit/io/common/expiry_pb2_grpc.py
passkit/io/common/filter_pb2.py
passkit/io/common/filter_pb2_grpc.py
passkit/io/common/integration_pb2.py
passkit/io/common/integration_pb2_grpc.py
passkit/io/common/links_pb2.py
passkit/io/common/links_pb2_grpc.py
passkit/io/common/localization_pb2.py
passkit/io/common/localization_pb2_grpc.py
passkit/io/common/message_pb2.py
passkit/io/common/message_pb2_grpc.py
passkit/io/common/metrics_pb2.py
passkit/io/common/metrics_pb2_grpc.py
passkit/io/common/note_pb2.py
passkit/io/common/note_pb2_grpc.py
passkit/io/common/operation_pb2.py
passkit/io/common/operation_pb2_grpc.py
passkit/io/common/pagination_pb2.py
passkit/io/common/pagination_pb2_grpc.py
passkit/io/common/pass_pb2.py
passkit/io/common/pass_pb2_grpc.py
passkit/io/common/personal_pb2.py
passkit/io/common/personal_pb2_grpc.py
passkit/io/common/project_pb2.py
passkit/io/common/project_pb2_grpc.py
passkit/io/common/protocols_pb2.py
passkit/io/common/protocols_pb2_grpc.py
passkit/io/common/proximity_pb2.py
passkit/io/common/proximity_pb2_grpc.py
passkit/io/common/reporting_pb2.py
passkit/io/common/reporting_pb2_grpc.py
passkit/io/common/semantics_pb2.py
passkit/io/common/semantics_pb2_grpc.py
passkit_python_grpc_sdk-1.1.123.5.dist-info/METADATA
passkit_python_grpc_sdk-1.1.123.5.dist-info/WHEEL
passkit_python_grpc_sdk-1.1.123.5.dist-info/RECORD
