Metadata-Version: 2.4
Name: passkit-python-grpc-sdk
Version: 1.1.123.5
Summary: Python SDK for Apple Wallet and Google Pay Membership / Loyalty / Access Cards, Coupons, Flights & Event-Tickets.
Project-URL: Homepage, https://github.com/PassKit/passkit-python-grpc-sdk
Project-URL: Bug Tracker, https://github.com/PassKit/passkit-python-grpc-sdk/issues
Author-email: passkit <support@passkit.com>
Classifier: License :: OSI Approved :: MIT License
Classifier: Operating System :: OS Independent
Classifier: Programming Language :: Python :: 3
Requires-Python: >=3.7
